mcp_utils/__init__.py
mcp_utils/core.py
mcp_utils/queue.py
mcp_utils/schema.py
mcp_utils/utils.py
mcp_utils-1.0.0.dist-info/METADATA
mcp_utils-1.0.0.dist-info/WHEEL
mcp_utils-1.0.0.dist-info/licenses/LICENSE
mcp_utils-1.0.0.dist-info/RECORD
