Metadata-Version: 2.4
Name: mcp-utils
Version: 1.0.0
Summary: Synchronous utilities for Model Context Protocol (MCP) integration
Project-URL: Homepage, https://github.com/fulfilio/mcp-utils
Project-URL: Repository, https://github.com/fulfilio/mcp-utils.git
Author: Fulfil.IO Inc
License-Expression: MIT
License-File: LICENSE
Keywords: ai,llm,mcp,model-context-protocol
Classifier: Development Status :: 3 - Alpha
Classifier: Intended Audience :: Developers
Classifier: License :: OSI Approved :: MIT License
Classifier: Programming Language :: Python :: 3
Classifier: Programming Language :: Python :: 3.10
Classifier: Programming Language :: Python :: 3.11
Requires-Python: >=3.10
Requires-Dist: pydantic>=2.0.0
Provides-Extra: dev
Requires-Dist: bump-my-version>=0.15.0; extra == 'dev'
Requires-Dist: pre-commit>=3.6.0; extra == 'dev'
Requires-Dist: pytest-cov>=4.1.0; extra == 'dev'
Requires-Dist: pytest>=8.0.0; extra == 'dev'
Requires-Dist: ruff>=0.3.0; extra == 'dev'
